df_graph_construction/__init__.py
df_graph_construction/cli.py
df_graph_construction/cluster2vec/__init__.py
df_graph_construction/cluster2vec/build.py
df_graph_construction/cluster2vec/embeddings.py
df_graph_construction/cluster2vec/merge_clusters.py
df_graph_construction/clustering/__init__.py
df_graph_construction/clustering/biclustering.py
df_graph_construction/clustering/filters.py
df_graph_construction/clustering/gmm_clustering.py
df_graph_construction/clustering/hierarchical_clustering.py
df_graph_construction/clustering/interface.py
df_graph_construction/clustering/interpret.py
df_graph_construction/clustering/kmeans_clustering.py
df_graph_construction/clustering/metrics.py
df_graph_construction/clustering/precomputed_merge_clustering.py
df_graph_construction/clustering/random_clustering.py
df_graph_construction/clustering/sklearn_clustering.py
df_graph_construction/clustering/subclustering.py
df_graph_construction/dataset/__init__.py
df_graph_construction/dataset/dataset.py
df_graph_construction/dataset/multiwoz.py
df_graph_construction/dialogue_graph/__init__.py
df_graph_construction/dialogue_graph/dgac.py
df_graph_construction/dialogue_graph/dialogue2json.py
df_graph_construction/dialogue_graph/frequency_dialogue_graph.py
df_graph_construction/embedders/__init__.py
df_graph_construction/embedders/bert_embedder.py
df_graph_construction/embedders/cached_embedder.py
df_graph_construction/embedders/convert.py
df_graph_construction/embedders/convert_embedder.py
df_graph_construction/embedders/interface.py
df_graph_construction/embedders/sentence_embedder.py
df_graph_construction/embedders/tfidf_embedder.py
df_graph_construction-0.1.0.dist-info/LICENSE
df_graph_construction-0.1.0.dist-info/METADATA
df_graph_construction-0.1.0.dist-info/WHEEL
df_graph_construction-0.1.0.dist-info/entry_points.txt
df_graph_construction-0.1.0.dist-info/top_level.txt
df_graph_construction-0.1.0.dist-info/RECORD
