Metadata-Version: 2.1
Name: df-graph-construction
Version: 0.1.0
Summary: **Dialog Flow Graph Construction** is python module add-on for [Dialog Flow Framework](https://github.com/deepmipt/dialog_flow_framework), a free and open-source software stack for creating chatbots, released under the terms of Apache License 2.0.
Home-page: https://github.com/deepmipt/dialog_flow_graph_construction
Author: Denis Kuznetosv
Author-email: kuznetsov.den.p@gmail.com
Keywords: chatbots,Dialog Flow Graph Construction
Classifier: Development Status :: 2 - Pre-Alpha
Classifier: Intended Audience :: Developers
Classifier: Topic :: Software Development :: Build Tools
Classifier: License :: OSI Approved :: Apache Software License
Classifier: Operating System :: OS Independent
Classifier: Programming Language :: Python :: 3
Classifier: Programming Language :: Python :: 3.6
Classifier: Programming Language :: Python :: 3.7
Classifier: Programming Language :: Python :: 3.8
Classifier: Programming Language :: Python :: 3.9
Classifier: Programming Language :: Python :: 3 :: Only
Requires-Python: >=3.6, <4
License-File: LICENSE
Requires-Dist: numpy (>=1.19.5)
Requires-Dist: scikit-learn (>=0.24.2)
Requires-Dist: datasets (==2.2.2)
Requires-Dist: sentence-transformers (==2.2.0)
